symphony_ui/__init__.py
symphony_ui/_frontend.py
symphony_ui/_helpers.py
symphony_ui/_specs.py
symphony_ui/_version.py
symphony_ui/_widgets.py
symphony_ui/symphony.py
symphony_ui/labextension/build_log.json
symphony_ui/labextension/package.json
symphony_ui/labextension/static/lib_index_js.5bebf761c9e7f7d601e7.js
symphony_ui/labextension/static/lib_index_js.5bebf761c9e7f7d601e7.js.map
symphony_ui/labextension/static/lib_index_js.dd64b7a60151c063f087.js
symphony_ui/labextension/static/lib_index_js.dd64b7a60151c063f087.js.map
symphony_ui/labextension/static/remoteEntry.747cf625af3d316d019b.js
symphony_ui/labextension/static/remoteEntry.747cf625af3d316d019b.js.map
symphony_ui/labextension/static/remoteEntry.82ea6fdc855c2c245cd7.js
symphony_ui/labextension/static/remoteEntry.82ea6fdc855c2c245cd7.js.map
symphony_ui/labextension/static/style.js
symphony_ui/nbextension/extension.js
symphony_ui/nbextension/index.js
symphony_ui/standalone/favicon.png
symphony_ui/standalone/index.html
symphony_ui/standalone/widgets/StandaloneApp.js
symphony_ui/standalone/widgets/StandaloneApp.js.map
symphony_ui-1.0.1.data/data/etc/jupyter/nbconfig/notebook.d/symphony_ui.json
symphony_ui-1.0.1.data/data/share/jupyter/labextensions/symphony_ui/build_log.json
symphony_ui-1.0.1.data/data/share/jupyter/labextensions/symphony_ui/install.json
symphony_ui-1.0.1.data/data/share/jupyter/labextensions/symphony_ui/package.json
symphony_ui-1.0.1.data/data/share/jupyter/labextensions/symphony_ui/static/lib_index_js.dd64b7a60151c063f087.js
symphony_ui-1.0.1.data/data/share/jupyter/labextensions/symphony_ui/static/lib_index_js.dd64b7a60151c063f087.js.map
symphony_ui-1.0.1.data/data/share/jupyter/labextensions/symphony_ui/static/remoteEntry.82ea6fdc855c2c245cd7.js
symphony_ui-1.0.1.data/data/share/jupyter/labextensions/symphony_ui/static/remoteEntry.82ea6fdc855c2c245cd7.js.map
symphony_ui-1.0.1.data/data/share/jupyter/labextensions/symphony_ui/static/style.js
symphony_ui-1.0.1.dist-info/LICENSE.txt
symphony_ui-1.0.1.dist-info/METADATA
symphony_ui-1.0.1.dist-info/WHEEL
symphony_ui-1.0.1.dist-info/top_level.txt
symphony_ui-1.0.1.dist-info/RECORD
